LICENSE
README.md
setup.cfg
setup.py
rail_label/__init__.py
rail_label/__main__.py
rail_label/label_gui.py
rail_label.egg-info/PKG-INFO
rail_label.egg-info/SOURCES.txt
rail_label.egg-info/dependency_links.txt
rail_label.egg-info/requires.txt
rail_label.egg-info/top_level.txt
rail_label/labeling/__init__.py
rail_label/labeling/gui/__init__.py
rail_label/labeling/gui/simple_gui.py
rail_label/labeling/scene/__init__.py
rail_label/labeling/scene/crosshair.py
rail_label/labeling/scene/point.py
rail_label/labeling/scene/scene.py
rail_label/labeling/scene/stencil.py
rail_label/labeling/switch/__init__.py
rail_label/labeling/switch/switch.py
rail_label/labeling/track/__init__.py
rail_label/labeling/track/legacy_converter.py
rail_label/labeling/track/rail.py
rail_label/labeling/track/segmentation_label.py
rail_label/labeling/track/track.py
rail_label/utils/__init__.py
rail_label/utils/camera.py
rail_label/utils/data_set.py
rail_label/utils/geometry.py
rail_label/utils/mouse.py