Metadata-Version: 2.1
Name: rail-label
Version: 0.1.2
Summary: Perspective label tool for railways
Home-page: UNKNOWN
Author: Florian Hofstetter
Author-email: <flo.max.hofstetter@gmail.com>
License: UNKNOWN
Keywords: python,video,railway,rail,train,labeling
Platform: UNKNOWN
Classifier: Development Status :: 1 - Planning
Classifier: Intended Audience :: Developers
Classifier: Programming Language :: Python :: 3.9
Classifier: Operating System :: Unix
Classifier: Operating System :: MacOS :: MacOS X
Classifier: Operating System :: Microsoft :: Windows
License-File: LICENSE
